granular/__init__.py
granular/geometry.py
granular/grain.py
granular-0.0.0.dist-info/LICENSE
granular-0.0.0.dist-info/METADATA
granular-0.0.0.dist-info/WHEEL
granular-0.0.0.dist-info/top_level.txt
granular-0.0.0.dist-info/RECORD
